unwebpack_sourcemap.py
unwebpack_sourcemap-0.0.3.dist-info/entry_points.txt
unwebpack_sourcemap-0.0.3.dist-info/METADATA
unwebpack_sourcemap-0.0.3.dist-info/WHEEL
unwebpack_sourcemap-0.0.3.dist-info/LICENSE
unwebpack_sourcemap-0.0.3.dist-info/RECORD
