Metadata-Version: 2.1
Name: unwebpack-sourcemap
Version: 0.0.3
Summary: Recovers uncompiled TypeScript sources from Webpack sourcemaps. A fork of rarecoil's work.
License: MIT
Author: James Mishra
Author-email: j@jamesmishra.com
Requires-Python: >=3.8,<3.12
Classifier: License :: OSI Approved :: MIT License
Classifier: Programming Language :: Python :: 3
Classifier: Programming Language :: Python :: 3.8
Classifier: Programming Language :: Python :: 3.9
Classifier: Programming Language :: Python :: 3.10
Classifier: Programming Language :: Python :: 3.11
Requires-Dist: beautifulsoup4 (==4.7.1)
Requires-Dist: certifi (>=2022.12.7)
Requires-Dist: chardet (==3.0.4)
Requires-Dist: idna (==2.8)
Requires-Dist: requests (==2.22.0)
Requires-Dist: soupsieve
Requires-Dist: urllib3
